argparsedecorator/__init__.py
argparsedecorator/annotations.py
argparsedecorator/argparse_decorator.py
argparsedecorator/argument.py
argparsedecorator/nonexiting_argumentparser.py
argparsedecorator/parsernode.py
ArgParseDecorator-1.4.0.dist-info/LICENSE.txt
ArgParseDecorator-1.4.0.dist-info/METADATA
ArgParseDecorator-1.4.0.dist-info/WHEEL
ArgParseDecorator-1.4.0.dist-info/top_level.txt
ArgParseDecorator-1.4.0.dist-info/RECORD
