Metadata-Version: 2.1
Name: ArgParseDecorator
Version: 1.4.0
Summary: A tool to easily build command line interpreters
Home-page: https://github.com/innot/argparseDecorator
Author: Thomas Holland
Author-email: thomas@innot.de
License: MIT
Project-URL: Documentation, https://argparsedecorator.readthedocs.io/en/latest/
Project-URL: Bug Tracker, https://github.com/innot/argparseDecorator/issues
Keywords: 'argparse ArgumentParser decorator tool cli commandline'
Classifier: Development Status :: 5 - Production/Stable
Classifier: Programming Language :: Python :: 3.8
Classifier: Programming Language :: Python :: 3.9
Classifier: Programming Language :: Python :: 3.10
Classifier: Programming Language :: Python :: 3.11
Classifier: Programming Language :: Python :: 3.12
Classifier: License :: OSI Approved :: MIT License
Classifier: Operating System :: OS Independent
Classifier: Intended Audience :: Developers
Classifier: Natural Language :: English
Classifier: Topic :: Software Development
Classifier: Topic :: System :: Shells
Classifier: Topic :: Utilities
License-File: LICENSE.txt
Provides-Extra: examples
Requires-Dist: asyncssh ; extra == 'examples'
Requires-Dist: prompt-toolkit ; extra == 'examples'
